xiezhi/__init__.py
xiezhi/main.py
xiezhi_ai-0.0.0.dist-info/METADATA
xiezhi_ai-0.0.0.dist-info/WHEEL
xiezhi_ai-0.0.0.dist-info/top_level.txt
xiezhi_ai-0.0.0.dist-info/RECORD
