Metadata-Version: 2.1
Name: xiezhi-ai
Version: 0.0.0
Summary: Anomaly detection for one-dimensional data
Author: Zhilin Wang
Author-email: wang5327@purdue.edu
License: MIT
Keywords: python,anomaly detection,one-dimentional data
Requires-Dist: numpy
